[
  {
    "id": "color-contrast",
    "title": "Background and foreground colors do not have a sufficient contrast ratio.",
    "description": "Low-contrast text is difficult or impossible for many users to read. [Learn how to provide sufficient color contrast](https://dequeuniversity.com/rules/axe/4.10/color-contrast).",
    "score": 0,
    "scoreDisplayMode": "binary",
    "details": {
      "type": "table",
      "headings": [
        {
          "key": "node",
          "valueType": "node",
          "subItemsHeading": {
            "key": "relatedNode",
            "valueType": "node"
          },
          "label": "Failing Elements"
        }
      ],
      "items": [
        {
          "node": {
            "type": "node",
            "lhId": "1-0-SPAN",
            "path": "1,HTML,1,BODY,6,DIV,2,DIV,0,DIV,0,DIV,0,MAIN,0,ARTICLE,2,DIV,1,DIV,0,DIV,0,DIV,0,DIV,1,DIV,0,SPAN",
            "selector": "div.fc-header > div.fc-header-row > div.fc-header-cell > span.fc-button",
            "boundingRect": {
              "top": 190,
              "bottom": 240,
              "left": 21,
              "right": 391,
              "width": 370,
              "height": 50
            },
            "snippet": "<span class=\"fc-button fc-button-rhc_search fc-state-default fc-corner-left fc-corner-r…\" unselectable=\"on\">",
            "nodeLabel": "Calendar",
            "explanation": "Fix any of the following:\n  Element has insufficient color contrast of 3.15 (foreground color: #ffffff, background color: #3498db, font size: 12.0pt (16px), font weight: normal). Expected contrast ratio of 4.5:1"
          }
        },
        {
          "node": {
            "type": "node",
            "lhId": "1-1-SPAN",
            "path": "1,HTML,1,BODY,6,DIV,2,DIV,0,DIV,0,DIV,0,MAIN,0,ARTICLE,2,DIV,1,DIV,0,DIV,0,DIV,0,DIV,1,DIV,7,SPAN",
            "selector": "div.fc-header > div.fc-header-row > div.fc-header-cell > span.fc-button",
            "boundingRect": {
              "top": 292,
              "bottom": 343,
              "left": 21,
              "right": 391,
              "width": 370,
              "height": 50
            },
            "snippet": "<span class=\"fc-button fc-button-today fc-state-default fc-corner-left fc-corner-right …\" unselectable=\"on\">",
            "nodeLabel": "today",
            "explanation": "Fix any of the following:\n  Element has insufficient color contrast of 2.05 (foreground color: #ffffff, background color: #7bbce8, font size: 12.0pt (16px), font weight: normal). Expected contrast ratio of 4.5:1"
          },
          "subItems": {
            "type": "subitems",
            "items": [
              {
                "relatedNode": {
                  "type": "node",
                  "lhId": "1-2-BODY",
                  "path": "1,HTML,1,BODY",
                  "selector": "body.page-template-default",
                  "boundingRect": {
                    "top": 0,
                    "bottom": 4009,
                    "left": 0,
                    "right": 412,
                    "width": 412,
                    "height": 4009
                  },
                  "snippet": "<body data-rsssl=\"1\" itemtype=\"https://schema.org/WebPage\" itemscope=\"itemscope\" class=\"page-template-default page page-id-4905 wp-custom-logo tribe-js tec-no-tic…\" style=\"\">",
                  "nodeLabel": "body.page-template-default"
                }
              }
            ]
          }
        },
        {
          "node": {
            "type": "node",
            "lhId": "1-3-SPAN",
            "path": "1,HTML,1,BODY,6,DIV,2,DIV,0,DIV,0,DIV,0,MAIN,0,ARTICLE,2,DIV,1,DIV,0,DIV,0,DIV,0,DIV,2,DIV,1,SPAN",
            "selector": "div.fc-header > div.fc-header-row > div.fc-header-cell > span.fc-button",
            "boundingRect": {
              "top": 397,
              "bottom": 448,
              "left": 21,
              "right": 391,
              "width": 370,
              "height": 50
            },
            "snippet": "<span class=\"fc-button fc-button-agendaWeek fc-state-default\" unselectable=\"on\">",
            "nodeLabel": "week",
            "explanation": "Fix any of the following:\n  Element has insufficient color contrast of 3.15 (foreground color: #ffffff, background color: #3498db, font size: 12.0pt (16px), font weight: normal). Expected contrast ratio of 4.5:1"
          }
        },
        {
          "node": {
            "type": "node",
            "lhId": "1-4-SPAN",
            "path": "1,HTML,1,BODY,6,DIV,2,DIV,0,DIV,0,DIV,0,MAIN,0,ARTICLE,2,DIV,1,DIV,0,DIV,0,DIV,0,DIV,2,DIV,2,SPAN",
            "selector": "div.fc-header > div.fc-header-row > div.fc-header-cell > span.fc-button",
            "boundingRect": {
              "top": 450,
              "bottom": 500,
              "left": 21,
              "right": 391,
              "width": 370,
              "height": 50
            },
            "snippet": "<span class=\"fc-button fc-button-agendaDay fc-state-default\" unselectable=\"on\">",
            "nodeLabel": "day",
            "explanation": "Fix any of the following:\n  Element has insufficient color contrast of 3.15 (foreground color: #ffffff, background color: #3498db, font size: 12.0pt (16px), font weight: normal). Expected contrast ratio of 4.5:1"
          }
        },
        {
          "node": {
            "type": "node",
            "lhId": "1-5-SPAN",
            "path": "1,HTML,1,BODY,6,DIV,2,DIV,0,DIV,0,DIV,0,MAIN,0,ARTICLE,2,DIV,1,DIV,0,DIV,0,DIV,0,DIV,2,DIV,3,SPAN",
            "selector": "div.fc-header > div.fc-header-row > div.fc-header-cell > span.fc-button",
            "boundingRect": {
              "top": 502,
              "bottom": 552,
              "left": 21,
              "right": 392,
              "width": 371,
              "height": 50
            },
            "snippet": "<span class=\"fc-button fc-button-rhc_event fc-state-default fc-corner-right\" unselectable=\"on\">",
            "nodeLabel": "event",
            "explanation": "Fix any of the following:\n  Element has insufficient color contrast of 3.15 (foreground color: #ffffff, background color: #3498db, font size: 12.0pt (16px), font weight: normal). Expected contrast ratio of 4.5:1"
          }
        },
        {
          "node": {
            "type": "node",
            "lhId": "1-6-SPAN",
            "path": "1,HTML,1,BODY,6,DIV,2,DIV,0,DIV,0,DIV,0,MAIN,0,ARTICLE,2,DIV,1,DIV,0,DIV,5,DIV,0,SPAN,0,SPAN,0,SPAN",
            "selector": "div.fc-footer > span.fc-button > span.fc-button-inner > span.fc-button-content",
            "boundingRect": {
              "top": 2573,
              "bottom": 2591,
              "left": 312,
              "right": 377,
              "width": 65,
              "height": 18
            },
            "snippet": "<span class=\"fc-button-content\">",
            "nodeLabel": "iCal Feed",
            "explanation": "Fix any of the following:\n  Element has insufficient color contrast of 3.15 (foreground color: #ffffff, background color: #3498db, font size: 12.0pt (16px), font weight: normal). Expected contrast ratio of 4.5:1"
          },
          "subItems": {
            "type": "subitems",
            "items": [
              {
                "relatedNode": {
                  "type": "node",
                  "lhId": "1-7-SPAN",
                  "path": "1,HTML,1,BODY,6,DIV,2,DIV,0,DIV,0,DIV,0,MAIN,0,ARTICLE,2,DIV,1,DIV,0,DIV,5,DIV,0,SPAN",
                  "selector": "div#calendarize_0 > div.fullCalendar > div.fc-footer > span.fc-button",
                  "boundingRect": {
                    "top": 2562,
                    "bottom": 2603,
                    "left": 297,
                    "right": 392,
                    "width": 95,
                    "height": 41
                  },
                  "snippet": "<span class=\"fc-button fc-button-icalendar fc-state-default fc-corner-left fc-corner-ri…\">",
                  "nodeLabel": "iCal Feed"
                }
              }
            ]
          }
        }
      ],
      "debugData": {
        "type": "debugdata",
        "impact": "serious",
        "tags": [
          "cat.color",
          "wcag2aa",
          "wcag143",
          "TTv5",
          "TT13.c",
          "EN-301-549",
          "EN-9.1.4.3",
          "ACT"
        ]
      }
    },
    "errorCount": 6
  },
  {
    "id": "frame-title",
    "title": "`<frame>` or `<iframe>` elements do not have a title",
    "description": "Screen reader users rely on frame titles to describe the contents of frames. [Learn more about frame titles](https://dequeuniversity.com/rules/axe/4.10/frame-title).",
    "score": 0,
    "scoreDisplayMode": "binary",
    "details": {
      "type": "table",
      "headings": [
        {
          "key": "node",
          "valueType": "node",
          "subItemsHeading": {
            "key": "relatedNode",
            "valueType": "node"
          },
          "label": "Failing Elements"
        }
      ],
      "items": [
        {
          "node": {
            "type": "node",
            "lhId": "1-8-IFRAME",
            "path": "1,HTML,1,BODY,6,DIV,4,FOOTER,0,DIV,0,DIV,0,DIV,0,DIV,0,ASIDE,1,SECTION,0,DIV,1,DIV,0,IFRAME",
            "selector": "section#text-2 > div.textwidget > div.twocol-one > iframe",
            "boundingRect": {
              "top": 2871,
              "bottom": 3021,
              "left": 100,
              "right": 312,
              "width": 212,
              "height": 150
            },
            "snippet": "<iframe src=\"https://cdn.yoshki.com/iframe/54732.html\" frameborder=\"0\" scrolling=\"no\" data-mce-fragment=\"1\">",
            "nodeLabel": "section#text-2 > div.textwidget > div.twocol-one > iframe",
            "explanation": "Fix any of the following:\n  Element has no title attribute\n  aria-label attribute does not exist or is empty\n  aria-labelledby attribute does not exist, references elements that do not exist or references elements that are empty\n  Element's default semantics were not overridden with role=\"none\" or role=\"presentation\""
          }
        }
      ],
      "debugData": {
        "type": "debugdata",
        "impact": "serious",
        "tags": [
          "cat.text-alternatives",
          "wcag2a",
          "wcag412",
          "section508",
          "section508.22.i",
          "TTv5",
          "TT12.d",
          "EN-301-549",
          "EN-9.4.1.2"
        ]
      }
    },
    "errorCount": 1
  },
  {
    "id": "tabindex",
    "title": "Some elements have a `[tabindex]` value greater than 0",
    "description": "A value greater than 0 implies an explicit navigation ordering. Although technically valid, this often creates frustrating experiences for users who rely on assistive technologies. [Learn more about the `tabindex` attribute](https://dequeuniversity.com/rules/axe/4.10/tabindex).",
    "score": 0,
    "scoreDisplayMode": "binary",
    "details": {
      "type": "table",
      "headings": [
        {
          "key": "node",
          "valueType": "node",
          "subItemsHeading": {
            "key": "relatedNode",
            "valueType": "node"
          },
          "label": "Failing Elements"
        }
      ],
      "items": [
        {
          "node": {
            "type": "node",
            "lhId": "1-9-A",
            "path": "1,HTML,1,BODY,0,A",
            "selector": "body.page-template-default > a#pojo-a11y-skip-content",
            "boundingRect": {
              "top": -18970,
              "bottom": -18941,
              "left": 0,
              "right": 116,
              "width": 116,
              "height": 28
            },
            "snippet": "<a id=\"pojo-a11y-skip-content\" class=\"pojo-skip-link pojo-skip-content\" tabindex=\"1\" accesskey=\"s\" href=\"#content\">",
            "nodeLabel": "Skip to content",
            "explanation": "Fix any of the following:\n  Element has a tabindex greater than 0"
          }
        }
      ],
      "debugData": {
        "type": "debugdata",
        "impact": "serious",
        "tags": [
          "cat.keyboard",
          "best-practice"
        ]
      }
    },
    "errorCount": 1
  }
]